alchemyql/__init__.py
alchemyql/engine.py
alchemyql/errors.py
alchemyql/fastapi/__init__.py
alchemyql/fastapi/router.py
alchemyql/filters.py
alchemyql/models.py
alchemyql/py.typed
alchemyql/register.py
alchemyql/resolver.py
alchemyql/scalars.py
alchemyql/schema.py
alchemyql-0.0.1a4.dist-info/licenses/LICENSE
alchemyql-0.0.1a4.dist-info/WHEEL
alchemyql-0.0.1a4.dist-info/METADATA
alchemyql-0.0.1a4.dist-info/RECORD
