Metadata-Version: 2.4
Name: alchemyql
Version: 0.0.1a4
Summary: Lightweight Graph QL engine powered by SQL Alchemy
Keywords: graphql,sqlalchemy,database,graphql-engine
Author: Nicholas Williams
Author-email: Nicholas Williams <noreply@users.noreply.github.com>
License-Expression: MIT
License-File: LICENSE
Classifier: Programming Language :: Python :: 3
Classifier: Programming Language :: Python :: 3.12
Classifier: Programming Language :: Python :: 3.13
Classifier: Programming Language :: Python :: 3.14
Classifier: Operating System :: OS Independent
Classifier: Typing :: Typed
Requires-Dist: graphql-core>=3.2.4
Requires-Dist: sqlalchemy>=2.0.35
Requires-Dist: fastapi>=0.110.0 ; extra == 'fastapi'
Requires-Python: >=3.12
Provides-Extra: fastapi
